odoo8_addon_base_geoengine-8.0.0.4.0-py2.7-nspkg.pth
odoo8_addon_base_geoengine-8.0.0.4.0.dist-info/DESCRIPTION.rst
odoo8_addon_base_geoengine-8.0.0.4.0.dist-info/METADATA
odoo8_addon_base_geoengine-8.0.0.4.0.dist-info/RECORD
odoo8_addon_base_geoengine-8.0.0.4.0.dist-info/WHEEL
odoo8_addon_base_geoengine-8.0.0.4.0.dist-info/metadata.json
odoo8_addon_base_geoengine-8.0.0.4.0.dist-info/namespace_packages.txt
odoo8_addon_base_geoengine-8.0.0.4.0.dist-info/top_level.txt
odoo_addons/base_geoengine/README.rst
odoo_addons/base_geoengine/__init__.py
odoo_addons/base_geoengine/__openerp__.py
odoo_addons/base_geoengine/fields.py
odoo_addons/base_geoengine/geo_db.py
odoo_addons/base_geoengine/geo_field.py
odoo_addons/base_geoengine/geo_line.py
odoo_addons/base_geoengine/geo_model.py
odoo_addons/base_geoengine/geo_multiline.py
odoo_addons/base_geoengine/geo_multipoint.py
odoo_addons/base_geoengine/geo_multipolygon.py
odoo_addons/base_geoengine/geo_operators.py
odoo_addons/base_geoengine/geo_point.py
odoo_addons/base_geoengine/geo_polygon.py
odoo_addons/base_geoengine/doc/Makefile
odoo_addons/base_geoengine/doc/make.bat
odoo_addons/base_geoengine/doc/build/.buildinfo
odoo_addons/base_geoengine/doc/build/api_doc.html
odoo_addons/base_geoengine/doc/build/genindex.html
odoo_addons/base_geoengine/doc/build/index.html
odoo_addons/base_geoengine/doc/build/installation.html
odoo_addons/base_geoengine/doc/build/objects.inv
odoo_addons/base_geoengine/doc/build/postgisify.html
odoo_addons/base_geoengine/doc/build/prerequisite.html
odoo_addons/base_geoengine/doc/build/py-modindex.html
odoo_addons/base_geoengine/doc/build/search.html
odoo_addons/base_geoengine/doc/build/searchindex.js
odoo_addons/base_geoengine/doc/build/what_is_geoengine.html
odoo_addons/base_geoengine/doc/build/.doctrees/api_doc.doctree
odoo_addons/base_geoengine/doc/build/.doctrees/environment.pickle
odoo_addons/base_geoengine/doc/build/.doctrees/index.doctree
odoo_addons/base_geoengine/doc/build/.doctrees/installation.doctree
odoo_addons/base_geoengine/doc/build/.doctrees/postgisify.doctree
odoo_addons/base_geoengine/doc/build/.doctrees/prerequisite.doctree
odoo_addons/base_geoengine/doc/build/.doctrees/what_is_geoengine.doctree
odoo_addons/base_geoengine/doc/build/.doctrees/_templates/prerequisite.doctree
odoo_addons/base_geoengine/doc/build/_images/core_architecture.jpg
