Metadata-Version: 2.0
Name: odoo8-addon-base-geoengine
Version: 8.0.0.4.0
Summary: Geospatial support for OpenERP
Home-page: http://openerp.camptocamp.com
Author: Camptocamp,ACSONE SA/NV,Odoo Community Association (OCA)
Author-email: support@odoo-community.org
License: AGPL-3
Platform: UNKNOWN
Classifier: Programming Language :: Python
Classifier: Framework :: Odoo
Classifier: License :: OSI Approved :: GNU Affero General Public License v3
Requires-Python: ~=2.7
Requires-Dist: geojson
Requires-Dist: odoo (<9.0a,>=8.0a)
Requires-Dist: shapely
